tr9780/__init__.py
tr9780/tr9780.py
tr9780-0.0.2.dist-info/LICENSE
tr9780-0.0.2.dist-info/METADATA
tr9780-0.0.2.dist-info/WHEEL
tr9780-0.0.2.dist-info/top_level.txt
tr9780-0.0.2.dist-info/RECORD
